itk_viewer_agave_renderer/__about__.py
itk_viewer_agave_renderer/__init__.py
itk_viewer_agave_renderer/renderer.py
itk_viewer_agave_renderer-0.0.6.dist-info/METADATA
itk_viewer_agave_renderer-0.0.6.dist-info/WHEEL
itk_viewer_agave_renderer-0.0.6.dist-info/RECORD
